themis.finals.attack.helper-1.0.0-py3.5-nspkg.pth
themis/finals/attack/helper/__about__.py
themis/finals/attack/helper/__init__.py
themis.finals.attack.helper-1.0.0.dist-info/DESCRIPTION.rst
themis.finals.attack.helper-1.0.0.dist-info/METADATA
themis.finals.attack.helper-1.0.0.dist-info/RECORD
themis.finals.attack.helper-1.0.0.dist-info/WHEEL
themis.finals.attack.helper-1.0.0.dist-info/entry_points.txt
themis.finals.attack.helper-1.0.0.dist-info/metadata.json
themis.finals.attack.helper-1.0.0.dist-info/namespace_packages.txt
themis.finals.attack.helper-1.0.0.dist-info/top_level.txt
