Metadata-Version: 2.0
Name: themis.finals.attack.helper
Version: 1.0.0
Summary: Themis Finals attack helper library
Home-page: https://github.com/aspyatkin/themis-finals-attack-helper-py
Author: Alexander Pyatkin
Author-email: aspyatkin@gmail.com
License: MIT
Platform: UNKNOWN
Requires-Dist: requests (>=2.11.1)
Requires-Dist: setuptools (>=0.8)
Requires-Dist: themis.finals.attack.result (<1.1.0,>=1.0.0)
